ms2rescore/__init__.py
ms2rescore/__main__.py
ms2rescore/_version.py
ms2rescore/config_parser.py
ms2rescore/core.py
ms2rescore/exceptions.py
ms2rescore/feature_generators/__init__.py
ms2rescore/feature_generators/base.py
ms2rescore/feature_generators/basic.py
ms2rescore/feature_generators/deeplc.py
ms2rescore/feature_generators/im2deep.py
ms2rescore/feature_generators/ionmob.py
ms2rescore/feature_generators/maxquant.py
ms2rescore/feature_generators/ms2pip.py
ms2rescore/gui/__init__.py
ms2rescore/gui/__main__.py
ms2rescore/gui/app.py
ms2rescore/gui/function2ctk.py
ms2rescore/gui/widgets.py
ms2rescore/package_data/__init__.py
ms2rescore/package_data/config_default.json
ms2rescore/package_data/config_default_tims.json
ms2rescore/package_data/config_schema.json
ms2rescore/package_data/img/__init__.py
ms2rescore/package_data/img/comments_icon_black.png
ms2rescore/package_data/img/comments_icon_white.png
ms2rescore/package_data/img/config_icon.png
ms2rescore/package_data/img/docs_icon_black.png
ms2rescore/package_data/img/docs_icon_white.png
ms2rescore/package_data/img/github_icon_black.png
ms2rescore/package_data/img/github_icon_white.png
ms2rescore/package_data/img/ms2rescore_logo.png
ms2rescore/package_data/img/program_icon.ico
ms2rescore/parse_psms.py
ms2rescore/parse_spectra.py
ms2rescore/report/__init__.py
ms2rescore/report/__main__.py
ms2rescore/report/charts.py
ms2rescore/report/generate.py
ms2rescore/report/templates/__init__.py
ms2rescore/report/templates/about.html
ms2rescore/report/templates/base.html
ms2rescore/report/templates/config.html
ms2rescore/report/templates/features.html
ms2rescore/report/templates/log.html
ms2rescore/report/templates/metadata.html
ms2rescore/report/templates/overview.html
ms2rescore/report/templates/stats-card.html
ms2rescore/report/templates/style.html
ms2rescore/report/templates/target-decoy.html
ms2rescore/report/templates/texts.toml
ms2rescore/report/utils.py
ms2rescore/rescoring_engines/__init__.py
ms2rescore-3.2.0.post1.dist-info/WHEEL
ms2rescore-3.2.0.post1.dist-info/entry_points.txt
ms2rescore-3.2.0.post1.dist-info/METADATA
ms2rescore-3.2.0.post1.dist-info/RECORD
