Metadata-Version: 2.3
Name: ms2rescore
Version: 3.2.0.post1
Summary:  Modular and user-friendly platform for AI-assisted rescoring of peptide identifications.
Keywords: MS2Rescore,MS2PIP,DeepLC,Percolator,proteomics,mass spectrometry,peptide identification,rescoring,machine learning
Author: Ralf Gabriels, Arthur Declercq, Ana Sílvia C. Silva, Robbin Bouwmeester, Louise Buur
Author-email: Ralf Gabriels <ralf@gabriels.dev>, Arthur Declercq <arthur.declercq@ugent.be>
License:                                  Apache License
Classifier: Intended Audience :: Science/Research
Classifier: License :: OSI Approved :: Apache Software License
Classifier: Operating System :: OS Independent
Classifier: Programming Language :: Python :: 3 :: Only
Classifier: Topic :: Scientific/Engineering :: Bio-Informatics
Classifier: Development Status :: 5 - Production/Stable
Requires-Dist: cascade-config>=0.4.0
Requires-Dist: click>=7
Requires-Dist: customtkinter>=5,<6
Requires-Dist: deeplc>=3.1
Requires-Dist: deeplcretrainer
Requires-Dist: im2deep>=0.3.1
Requires-Dist: jinja2>=3
Requires-Dist: lxml>=4.5
Requires-Dist: mokapot==0.10
Requires-Dist: ms2pip>=4.0.0
Requires-Dist: ms2rescore-rs>=0.4.3
Requires-Dist: numpy>=1.25
Requires-Dist: packaging>=25.0
Requires-Dist: pandas>=1
Requires-Dist: plotly>=5
Requires-Dist: psm-utils>=1.1
Requires-Dist: pyteomics>=4.7.2
Requires-Dist: rich>=12
Requires-Dist: tomli>=2 ; python_full_version < '3.11'
Requires-Dist: pyopenms>=3.3 ; extra == 'idxml'
Requires-Dist: ionmob>=0.2 ; extra == 'ionmob'
Requires-Dist: tensorflow ; extra == 'ionmob'
Requires-Python: >=3.10
Project-URL: CompOmics, https://www.compomics.com
Project-URL: GitHub, https://github.com/compomics/ms2rescore
Project-URL: PyPi, https://pypi.org/project/ms2rescore/
Project-URL: ReadTheDocs, https://ms2rescore.readthedocs.io
Provides-Extra: idxml
Provides-Extra: ionmob
